starmocks.py
starmocks-0.1.0.dist-info/LICENSE
starmocks-0.1.0.dist-info/WHEEL
starmocks-0.1.0.dist-info/METADATA
starmocks-0.1.0.dist-info/RECORD
