Metadata-Version: 2.1
Name: starmocks
Version: 0.1.0
Summary: 
License: MIT
Author: Pedro Werneck
Author-email: pjwerneck@gmail.com
Requires-Python: >=3.6,<4.0
Classifier: License :: OSI Approved :: MIT License
Classifier: Programming Language :: Python :: 3
Classifier: Programming Language :: Python :: 3.6
Classifier: Programming Language :: Python :: 3.7
Requires-Dist: attrdict (>=2.0,<3.0)
